pylivetrader/__init__.py
pylivetrader/__main__.py
pylivetrader/_version.py
pylivetrader/algorithm.py
pylivetrader/api.py
pylivetrader/errors.py
pylivetrader/loader.py
pylivetrader/protocol.py
pylivetrader/shell.py
pylivetrader/assets/__init__.py
pylivetrader/assets/assets.py
pylivetrader/assets/finder.py
pylivetrader/backend/__init__.py
pylivetrader/backend/alpaca.py
pylivetrader/backend/base.py
pylivetrader/data/__init__.py
pylivetrader/data/bardata.py
pylivetrader/data/data_portal.py
pylivetrader/executor/__init__.py
pylivetrader/executor/executor.py
pylivetrader/executor/realtimeclock.py
pylivetrader/finance/__init__.py
pylivetrader/finance/asset_restrictions.py
pylivetrader/finance/cancel_policy.py
pylivetrader/finance/commission.py
pylivetrader/finance/controls.py
pylivetrader/finance/execution.py
pylivetrader/finance/order.py
pylivetrader/finance/slippage.py
pylivetrader/misc/__init__.py
pylivetrader/misc/api_context.py
pylivetrader/misc/configloader.py
pylivetrader/misc/context_tricks.py
pylivetrader/misc/events.py
pylivetrader/misc/functional.py
pylivetrader/misc/input_validation.py
pylivetrader/misc/math_utils.py
pylivetrader/misc/memorize.py
pylivetrader/misc/migration_tool.py
pylivetrader/misc/parallel_utils.py
pylivetrader/misc/pd_utils.py
pylivetrader/misc/preprocess.py
pylivetrader/misc/security_list.py
pylivetrader/misc/sentinel.py
pylivetrader/misc/zipline_utils.py
pylivetrader/statestore/__init__.py
pylivetrader/testing/__init__.py
pylivetrader/testing/fixtures.py
pylivetrader/testing/smoke/__init__.py
pylivetrader/testing/smoke/backend.py
pylivetrader/testing/smoke/clock.py
pylivetrader/testing/smoke/harness.py
tests/__init__.py
tests/test_algorithm.py
tests/test_api.py
tests/test_loader.py
tests/test_protocol.py
tests/test_data/__init__.py
tests/test_data/test_bardata.py
tests/test_data/test_data_portal.py
tests/test_misc/__init__.py
tests/test_misc/test_configloader.py
pylivetrader-0.7.1.dist-info/LICENSE
pylivetrader-0.7.1.dist-info/METADATA
pylivetrader-0.7.1.dist-info/WHEEL
pylivetrader-0.7.1.dist-info/entry_points.txt
pylivetrader-0.7.1.dist-info/top_level.txt
pylivetrader-0.7.1.dist-info/RECORD
