Metadata-Version: 2.1
Name: pylivetrader
Version: 0.7.1
Summary: simple live trading framework
Home-page: https://github.com/alpacahq/pylivetrader.git
Author: Alpaca
Author-email: oss@alpaca.markets
License: Apache 2.0
Keywords: financial,zipline,pipeline,stock,screening,api,trade
Platform: UNKNOWN
Classifier: Development Status :: 3 - Alpha
Classifier: License :: OSI Approved :: Apache Software License
Classifier: Natural Language :: English
Classifier: Programming Language :: Python
Classifier: Programming Language :: Python :: 3.6
Classifier: Programming Language :: Python :: 3.7
Classifier: Operating System :: OS Independent
Classifier: Topic :: Office/Business :: Financial
Requires-Dist: PyYAML (<6,>=5)
Requires-Dist: alpaca-trade-api (==1.5.0)
Requires-Dist: astor (>=0.8.1)
Requires-Dist: bottleneck (>=1.3)
Requires-Dist: click (==8.0.1)
Requires-Dist: ipython (>=7)
Requires-Dist: logbook (>=1.5)
Requires-Dist: numpy (<=1.19.5)
Requires-Dist: pandas-datareader (<=0.8.1)
Requires-Dist: pandas (<=0.22.0,>=0.18.1)
Requires-Dist: pipeline-live (>=0.2.0)
Requires-Dist: pytz (>=2020.1)
Requires-Dist: scipy (<1.6.0)
Requires-Dist: statsmodels (==0.11.1)
Requires-Dist: trading-calendars (>=1.11)
